MANIFEST.in
README.md
setup.py
django_launch_page.egg-info/PKG-INFO
django_launch_page.egg-info/SOURCES.txt
django_launch_page.egg-info/dependency_links.txt
django_launch_page.egg-info/requires.txt
django_launch_page.egg-info/top_level.txt
launch_page/__init__.py
launch_page/admin.py
launch_page/forms.py
launch_page/models.py
launch_page/tests.py
launch_page/urls.py
launch_page/views.py
launch_page/migrations/0001_initial.py
launch_page/migrations/__init__.py
launch_page/static/javascripts/inquire.js
launch_page/templates/launch_page/base.html
launch_page/templates/launch_page/inquiry_form.html
launch_page/templates/launch_page/thanks.html