Metadata-Version: 1.0
Name: django-launch-page
Version: 0.1.0
Summary: 
